{
  "difficulty": "medium",
  "image_index": 15053,
  "total_shapes": 4,
  "shapes": [
    {
      "type": "square",
      "color": "pink",
      "size_category": "small",
      "position": [
        138,
        446
      ],
      "size_pixels": 38
    },
    {
      "type": "oval",
      "color": "teal",
      "size_category": "small",
      "position": [
        360,
        88
      ],
      "size_pixels": 46
    },
    {
      "type": "triangle",
      "color": "light_mint",
      "size_category": "large",
      "position": [
        158,
        175
      ],
      "size_pixels": 210
    },
    {
      "type": "star",
      "color": "pale_blue",
      "size_category": "small",
      "position": [
        419,
        270
      ],
      "size_pixels": 36
    }
  ]
}