{
  "difficulty": "medium",
  "image_index": 19920,
  "total_shapes": 5,
  "shapes": [
    {
      "type": "star",
      "color": "light_mint",
      "size_category": "large",
      "position": [
        126,
        335
      ],
      "size_pixels": 178
    },
    {
      "type": "square",
      "color": "teal",
      "size_category": "large",
      "position": [
        260,
        132
      ],
      "size_pixels": 210
    },
    {
      "type": "rectangle",
      "color": "light_green",
      "size_category": "small",
      "position": [
        433,
        430
      ],
      "size_pixels": 36
    },
    {
      "type": "oval",
      "color": "lavender",
      "size_category": "small",
      "position": [
        405,
        165
      ],
      "size_pixels": 42
    },
    {
      "type": "oval",
      "color": "orange",
      "size_category": "small",
      "position": [
        112,
        122
      ],
      "size_pixels": 32
    }
  ]
}