{
  "difficulty": "medium",
  "image_index": 5351,
  "total_shapes": 5,
  "shapes": [
    {
      "type": "oval",
      "color": "lavender",
      "size_category": "small",
      "position": [
        157,
        92
      ],
      "size_pixels": 32
    },
    {
      "type": "star",
      "color": "orange",
      "size_category": "small",
      "position": [
        425,
        453
      ],
      "size_pixels": 30
    },
    {
      "type": "square",
      "color": "soft_purple",
      "size_category": "small",
      "position": [
        220,
        438
      ],
      "size_pixels": 30
    },
    {
      "type": "star",
      "color": "pink",
      "size_category": "large",
      "position": [
        301,
        116
      ],
      "size_pixels": 186
    },
    {
      "type": "oval",
      "color": "orange",
      "size_category": "small",
      "position": [
        135,
        166
      ],
      "size_pixels": 44
    }
  ]
}