{
  "difficulty": "medium",
  "image_index": 7463,
  "total_shapes": 4,
  "shapes": [
    {
      "type": "square",
      "color": "yellow",
      "size_category": "small",
      "position": [
        156,
        288
      ],
      "size_pixels": 34
    },
    {
      "type": "rectangle",
      "color": "light_green",
      "size_category": "small",
      "position": [
        193,
        203
      ],
      "size_pixels": 42
    },
    {
      "type": "square",
      "color": "teal",
      "size_category": "small",
      "position": [
        428,
        119
      ],
      "size_pixels": 40
    },
    {
      "type": "oval",
      "color": "light_pink",
      "size_category": "large",
      "position": [
        259,
        361
      ],
      "size_pixels": 166
    }
  ]
}