{
  "difficulty": "medium",
  "image_index": 1255,
  "total_shapes": 4,
  "shapes": [
    {
      "type": "rectangle",
      "color": "light_green",
      "size_category": "small",
      "position": [
        91,
        184
      ],
      "size_pixels": 44
    },
    {
      "type": "rectangle",
      "color": "light_blue",
      "size_category": "small",
      "position": [
        48,
        339
      ],
      "size_pixels": 48
    },
    {
      "type": "oval",
      "color": "light_pink",
      "size_category": "large",
      "position": [
        217,
        114
      ],
      "size_pixels": 176
    },
    {
      "type": "triangle",
      "color": "lavender",
      "size_category": "large",
      "position": [
        352,
        344
      ],
      "size_pixels": 168
    }
  ]
}