{
  "difficulty": "medium",
  "image_index": 2971,
  "total_shapes": 5,
  "shapes": [
    {
      "type": "square",
      "color": "teal",
      "size_category": "large",
      "position": [
        186,
        356
      ],
      "size_pixels": 218
    },
    {
      "type": "square",
      "color": "soft_blue",
      "size_category": "large",
      "position": [
        120,
        130
      ],
      "size_pixels": 200
    },
    {
      "type": "square",
      "color": "yellow",
      "size_category": "small",
      "position": [
        406,
        358
      ],
      "size_pixels": 38
    },
    {
      "type": "triangle",
      "color": "pale_blue",
      "size_category": "small",
      "position": [
        321,
        94
      ],
      "size_pixels": 46
    },
    {
      "type": "rectangle",
      "color": "teal",
      "size_category": "small",
      "position": [
        351,
        201
      ],
      "size_pixels": 42
    }
  ]
}