{
  "difficulty": "medium",
  "image_index": 10578,
  "total_shapes": 5,
  "shapes": [
    {
      "type": "circle",
      "color": "teal",
      "size_category": "large",
      "position": [
        174,
        176
      ],
      "size_pixels": 194
    },
    {
      "type": "square",
      "color": "pink",
      "size_category": "large",
      "position": [
        363,
        371
      ],
      "size_pixels": 204
    },
    {
      "type": "oval",
      "color": "yellow",
      "size_category": "small",
      "position": [
        120,
        418
      ],
      "size_pixels": 48
    },
    {
      "type": "triangle",
      "color": "soft_blue",
      "size_category": "small",
      "position": [
        75,
        83
      ],
      "size_pixels": 32
    },
    {
      "type": "star",
      "color": "pink",
      "size_category": "small",
      "position": [
        325,
        72
      ],
      "size_pixels": 28
    }
  ]
}