{
  "difficulty": "medium",
  "image_index": 7031,
  "total_shapes": 4,
  "shapes": [
    {
      "type": "rectangle",
      "color": "mint",
      "size_category": "small",
      "position": [
        462,
        445
      ],
      "size_pixels": 34
    },
    {
      "type": "star",
      "color": "light_purple",
      "size_category": "small",
      "position": [
        86,
        327
      ],
      "size_pixels": 32
    },
    {
      "type": "square",
      "color": "light_green",
      "size_category": "small",
      "position": [
        220,
        117
      ],
      "size_pixels": 48
    },
    {
      "type": "circle",
      "color": "beige",
      "size_category": "small",
      "position": [
        362,
        435
      ],
      "size_pixels": 38
    }
  ]
}