{
  "difficulty": "medium",
  "image_index": 672,
  "total_shapes": 4,
  "shapes": [
    {
      "type": "rectangle",
      "color": "light_pink",
      "size_category": "small",
      "position": [
        320,
        129
      ],
      "size_pixels": 44
    },
    {
      "type": "star",
      "color": "light_green",
      "size_category": "small",
      "position": [
        57,
        280
      ],
      "size_pixels": 48
    },
    {
      "type": "circle",
      "color": "yellow",
      "size_category": "large",
      "position": [
        318,
        272
      ],
      "size_pixels": 188
    },
    {
      "type": "star",
      "color": "pink",
      "size_category": "small",
      "position": [
        178,
        236
      ],
      "size_pixels": 44
    }
  ]
}