{
  "difficulty": "medium",
  "image_index": 5690,
  "total_shapes": 4,
  "shapes": [
    {
      "type": "square",
      "color": "light_pink",
      "size_category": "small",
      "position": [
        159,
        457
      ],
      "size_pixels": 32
    },
    {
      "type": "star",
      "color": "yellow",
      "size_category": "small",
      "position": [
        372,
        452
      ],
      "size_pixels": 44
    },
    {
      "type": "circle",
      "color": "soft_blue",
      "size_category": "large",
      "position": [
        162,
        120
      ],
      "size_pixels": 166
    },
    {
      "type": "star",
      "color": "purple",
      "size_category": "small",
      "position": [
        418,
        295
      ],
      "size_pixels": 28
    }
  ]
}