{
  "difficulty": "medium",
  "image_index": 8876,
  "total_shapes": 4,
  "shapes": [
    {
      "type": "square",
      "color": "orange",
      "size_category": "small",
      "position": [
        410,
        387
      ],
      "size_pixels": 46
    },
    {
      "type": "star",
      "color": "light_mint",
      "size_category": "small",
      "position": [
        120,
        287
      ],
      "size_pixels": 42
    },
    {
      "type": "star",
      "color": "soft_purple",
      "size_category": "small",
      "position": [
        80,
        455
      ],
      "size_pixels": 50
    },
    {
      "type": "oval",
      "color": "beige",
      "size_category": "large",
      "position": [
        249,
        196
      ],
      "size_pixels": 208
    }
  ]
}