{
  "difficulty": "medium",
  "image_index": 19036,
  "total_shapes": 4,
  "shapes": [
    {
      "type": "star",
      "color": "beige",
      "size_category": "small",
      "position": [
        107,
        344
      ],
      "size_pixels": 42
    },
    {
      "type": "circle",
      "color": "soft_blue",
      "size_category": "large",
      "position": [
        316,
        183
      ],
      "size_pixels": 194
    },
    {
      "type": "star",
      "color": "pale_blue",
      "size_category": "small",
      "position": [
        443,
        84
      ],
      "size_pixels": 44
    },
    {
      "type": "circle",
      "color": "lavender",
      "size_category": "small",
      "position": [
        374,
        50
      ],
      "size_pixels": 44
    }
  ]
}