{
  "difficulty": "medium",
  "image_index": 8403,
  "total_shapes": 5,
  "shapes": [
    {
      "type": "oval",
      "color": "pale_mint",
      "size_category": "large",
      "position": [
        334,
        314
      ],
      "size_pixels": 208
    },
    {
      "type": "star",
      "color": "light_purple",
      "size_category": "small",
      "position": [
        170,
        352
      ],
      "size_pixels": 40
    },
    {
      "type": "circle",
      "color": "mint",
      "size_category": "small",
      "position": [
        200,
        103
      ],
      "size_pixels": 26
    },
    {
      "type": "triangle",
      "color": "pale_mint",
      "size_category": "small",
      "position": [
        124,
        63
      ],
      "size_pixels": 42
    },
    {
      "type": "oval",
      "color": "pale_mint",
      "size_category": "small",
      "position": [
        181,
        235
      ],
      "size_pixels": 48
    }
  ]
}