{
  "difficulty": "medium",
  "image_index": 1443,
  "total_shapes": 5,
  "shapes": [
    {
      "type": "rectangle",
      "color": "light_green",
      "size_category": "small",
      "position": [
        222,
        50
      ],
      "size_pixels": 48
    },
    {
      "type": "triangle",
      "color": "soft_blue",
      "size_category": "small",
      "position": [
        71,
        244
      ],
      "size_pixels": 50
    },
    {
      "type": "circle",
      "color": "soft_blue",
      "size_category": "small",
      "position": [
        341,
        241
      ],
      "size_pixels": 32
    },
    {
      "type": "square",
      "color": "teal",
      "size_category": "small",
      "position": [
        177,
        403
      ],
      "size_pixels": 44
    },
    {
      "type": "star",
      "color": "soft_blue",
      "size_category": "small",
      "position": [
        42,
        169
      ],
      "size_pixels": 28
    }
  ]
}