{
  "difficulty": "medium",
  "image_index": 16256,
  "total_shapes": 5,
  "shapes": [
    {
      "type": "triangle",
      "color": "orange",
      "size_category": "large",
      "position": [
        226,
        236
      ],
      "size_pixels": 200
    },
    {
      "type": "star",
      "color": "orange",
      "size_category": "small",
      "position": [
        94,
        416
      ],
      "size_pixels": 32
    },
    {
      "type": "rectangle",
      "color": "light_pink",
      "size_category": "small",
      "position": [
        420,
        444
      ],
      "size_pixels": 40
    },
    {
      "type": "rectangle",
      "color": "light_mint",
      "size_category": "small",
      "position": [
        82,
        265
      ],
      "size_pixels": 44
    },
    {
      "type": "star",
      "color": "soft_blue",
      "size_category": "small",
      "position": [
        74,
        365
      ],
      "size_pixels": 34
    }
  ]
}