{
  "difficulty": "medium",
  "image_index": 11749,
  "total_shapes": 5,
  "shapes": [
    {
      "type": "triangle",
      "color": "teal",
      "size_category": "small",
      "position": [
        158,
        450
      ],
      "size_pixels": 46
    },
    {
      "type": "triangle",
      "color": "light_green",
      "size_category": "large",
      "position": [
        282,
        369
      ],
      "size_pixels": 184
    },
    {
      "type": "triangle",
      "color": "teal",
      "size_category": "small",
      "position": [
        414,
        373
      ],
      "size_pixels": 38
    },
    {
      "type": "square",
      "color": "pale_mint",
      "size_category": "small",
      "position": [
        394,
        298
      ],
      "size_pixels": 28
    },
    {
      "type": "star",
      "color": "light_pink",
      "size_category": "small",
      "position": [
        75,
        191
      ],
      "size_pixels": 48
    }
  ]
}