{
  "difficulty": "medium",
  "image_index": 4918,
  "total_shapes": 5,
  "shapes": [
    {
      "type": "star",
      "color": "light_purple",
      "size_category": "small",
      "position": [
        292,
        405
      ],
      "size_pixels": 44
    },
    {
      "type": "star",
      "color": "yellow",
      "size_category": "small",
      "position": [
        451,
        76
      ],
      "size_pixels": 42
    },
    {
      "type": "square",
      "color": "light_green",
      "size_category": "small",
      "position": [
        443,
        356
      ],
      "size_pixels": 34
    },
    {
      "type": "star",
      "color": "light_mint",
      "size_category": "large",
      "position": [
        273,
        153
      ],
      "size_pixels": 210
    },
    {
      "type": "triangle",
      "color": "orange",
      "size_category": "small",
      "position": [
        398,
        295
      ],
      "size_pixels": 46
    }
  ]
}