{
  "difficulty": "medium",
  "image_index": 3588,
  "total_shapes": 4,
  "shapes": [
    {
      "type": "rectangle",
      "color": "mint",
      "size_category": "small",
      "position": [
        52,
        299
      ],
      "size_pixels": 32
    },
    {
      "type": "triangle",
      "color": "light_blue",
      "size_category": "large",
      "position": [
        375,
        342
      ],
      "size_pixels": 184
    },
    {
      "type": "square",
      "color": "orange",
      "size_category": "small",
      "position": [
        224,
        105
      ],
      "size_pixels": 46
    },
    {
      "type": "rectangle",
      "color": "light_mint",
      "size_category": "small",
      "position": [
        450,
        144
      ],
      "size_pixels": 42
    }
  ]
}