{
  "difficulty": "medium",
  "image_index": 14362,
  "total_shapes": 4,
  "shapes": [
    {
      "type": "circle",
      "color": "pale_mint",
      "size_category": "large",
      "position": [
        366,
        170
      ],
      "size_pixels": 206
    },
    {
      "type": "rectangle",
      "color": "pale_blue",
      "size_category": "small",
      "position": [
        345,
        325
      ],
      "size_pixels": 42
    },
    {
      "type": "square",
      "color": "purple",
      "size_category": "small",
      "position": [
        201,
        189
      ],
      "size_pixels": 34
    },
    {
      "type": "circle",
      "color": "lavender",
      "size_category": "small",
      "position": [
        56,
        445
      ],
      "size_pixels": 50
    }
  ]
}