{
  "difficulty": "medium",
  "image_index": 10430,
  "total_shapes": 5,
  "shapes": [
    {
      "type": "square",
      "color": "pale_mint",
      "size_category": "small",
      "position": [
        329,
        352
      ],
      "size_pixels": 44
    },
    {
      "type": "square",
      "color": "yellow",
      "size_category": "small",
      "position": [
        46,
        360
      ],
      "size_pixels": 28
    },
    {
      "type": "star",
      "color": "light_blue",
      "size_category": "small",
      "position": [
        446,
        211
      ],
      "size_pixels": 32
    },
    {
      "type": "rectangle",
      "color": "pale_blue",
      "size_category": "small",
      "position": [
        246,
        369
      ],
      "size_pixels": 28
    },
    {
      "type": "square",
      "color": "orange",
      "size_category": "small",
      "position": [
        237,
        54
      ],
      "size_pixels": 42
    }
  ]
}