{
  "difficulty": "medium",
  "image_index": 1876,
  "total_shapes": 5,
  "shapes": [
    {
      "type": "star",
      "color": "pink",
      "size_category": "small",
      "position": [
        241,
        317
      ],
      "size_pixels": 34
    },
    {
      "type": "circle",
      "color": "pink",
      "size_category": "large",
      "position": [
        120,
        145
      ],
      "size_pixels": 196
    },
    {
      "type": "square",
      "color": "light_green",
      "size_category": "small",
      "position": [
        269,
        188
      ],
      "size_pixels": 38
    },
    {
      "type": "square",
      "color": "light_mint",
      "size_category": "small",
      "position": [
        214,
        417
      ],
      "size_pixels": 42
    },
    {
      "type": "star",
      "color": "pink",
      "size_category": "small",
      "position": [
        108,
        439
      ],
      "size_pixels": 30
    }
  ]
}