{
  "difficulty": "medium",
  "image_index": 10662,
  "total_shapes": 5,
  "shapes": [
    {
      "type": "square",
      "color": "light_purple",
      "size_category": "small",
      "position": [
        381,
        446
      ],
      "size_pixels": 34
    },
    {
      "type": "triangle",
      "color": "light_blue",
      "size_category": "small",
      "position": [
        138,
        72
      ],
      "size_pixels": 40
    },
    {
      "type": "triangle",
      "color": "beige",
      "size_category": "small",
      "position": [
        324,
        48
      ],
      "size_pixels": 36
    },
    {
      "type": "triangle",
      "color": "purple",
      "size_category": "large",
      "position": [
        195,
        281
      ],
      "size_pixels": 168
    },
    {
      "type": "square",
      "color": "lavender",
      "size_category": "small",
      "position": [
        234,
        59
      ],
      "size_pixels": 40
    }
  ]
}