{
  "difficulty": "medium",
  "image_index": 17853,
  "total_shapes": 4,
  "shapes": [
    {
      "type": "oval",
      "color": "pale_blue",
      "size_category": "small",
      "position": [
        348,
        420
      ],
      "size_pixels": 50
    },
    {
      "type": "oval",
      "color": "teal",
      "size_category": "large",
      "position": [
        134,
        311
      ],
      "size_pixels": 194
    },
    {
      "type": "rectangle",
      "color": "pale_blue",
      "size_category": "small",
      "position": [
        339,
        309
      ],
      "size_pixels": 30
    },
    {
      "type": "star",
      "color": "teal",
      "size_category": "small",
      "position": [
        93,
        87
      ],
      "size_pixels": 32
    }
  ]
}