{
  "difficulty": "hard",
  "image_index": 4050,
  "total_shapes": 6,
  "shapes": [
    {
      "type": "diamond",
      "color": "light_mint",
      "size_category": "medium",
      "position": [
        358,
        97
      ],
      "size_pixels": 118
    },
    {
      "type": "square",
      "color": "light_mint",
      "size_category": "medium",
      "position": [
        168,
        297
      ],
      "size_pixels": 110
    },
    {
      "type": "diamond",
      "color": "pale_mint",
      "size_category": "small",
      "position": [
        540,
        173
      ],
      "size_pixels": 38
    },
    {
      "type": "rectangle",
      "color": "orange",
      "size_category": "medium",
      "position": [
        190,
        453
      ],
      "size_pixels": 142
    },
    {
      "type": "square",
      "color": "purple",
      "size_category": "small",
      "position": [
        245,
        351
      ],
      "size_pixels": 38
    },
    {
      "type": "star",
      "color": "pale_mint",
      "size_category": "small",
      "position": [
        505,
        523
      ],
      "size_pixels": 58
    }
  ]
}