{
  "difficulty": "hard",
  "image_index": 15423,
  "total_shapes": 7,
  "shapes": [
    {
      "type": "rectangle",
      "color": "orange",
      "size_category": "medium",
      "position": [
        249,
        387
      ],
      "size_pixels": 124
    },
    {
      "type": "heart",
      "color": "light_pink",
      "size_category": "large",
      "position": [
        340,
        156
      ],
      "size_pixels": 264
    },
    {
      "type": "circle",
      "color": "light_green",
      "size_category": "small",
      "position": [
        77,
        414
      ],
      "size_pixels": 56
    },
    {
      "type": "circle",
      "color": "beige",
      "size_category": "medium",
      "position": [
        451,
        329
      ],
      "size_pixels": 106
    },
    {
      "type": "diamond",
      "color": "light_green",
      "size_category": "small",
      "position": [
        356,
        546
      ],
      "size_pixels": 34
    },
    {
      "type": "diamond",
      "color": "orange",
      "size_category": "small",
      "position": [
        63,
        507
      ],
      "size_pixels": 34
    },
    {
      "type": "rectangle",
      "color": "pale_mint",
      "size_category": "medium",
      "position": [
        121,
        189
      ],
      "size_pixels": 124
    }
  ]
}