{
  "difficulty": "hard",
  "image_index": 7630,
  "total_shapes": 7,
  "shapes": [
    {
      "type": "hexagon",
      "color": "light_pink",
      "size_category": "medium",
      "position": [
        220,
        150
      ],
      "size_pixels": 98
    },
    {
      "type": "star",
      "color": "yellow",
      "size_category": "medium",
      "position": [
        448,
        238
      ],
      "size_pixels": 122
    },
    {
      "type": "pentagon",
      "color": "pale_mint",
      "size_category": "medium",
      "position": [
        270,
        300
      ],
      "size_pixels": 96
    },
    {
      "type": "star",
      "color": "pink",
      "size_category": "medium",
      "position": [
        403,
        434
      ],
      "size_pixels": 140
    },
    {
      "type": "square",
      "color": "light_mint",
      "size_category": "small",
      "position": [
        555,
        255
      ],
      "size_pixels": 40
    },
    {
      "type": "oval",
      "color": "pale_blue",
      "size_category": "small",
      "position": [
        528,
        58
      ],
      "size_pixels": 38
    },
    {
      "type": "triangle",
      "color": "soft_purple",
      "size_category": "small",
      "position": [
        289,
        413
      ],
      "size_pixels": 40
    }
  ]
}