{
  "difficulty": "hard",
  "image_index": 5373,
  "total_shapes": 7,
  "shapes": [
    {
      "type": "rectangle",
      "color": "pink",
      "size_category": "large",
      "position": [
        177,
        420
      ],
      "size_pixels": 266
    },
    {
      "type": "diamond",
      "color": "lavender",
      "size_category": "small",
      "position": [
        181,
        202
      ],
      "size_pixels": 46
    },
    {
      "type": "square",
      "color": "pale_mint",
      "size_category": "large",
      "position": [
        429,
        215
      ],
      "size_pixels": 250
    },
    {
      "type": "rectangle",
      "color": "yellow",
      "size_category": "medium",
      "position": [
        245,
        103
      ],
      "size_pixels": 92
    },
    {
      "type": "rectangle",
      "color": "soft_blue",
      "size_category": "small",
      "position": [
        497,
        424
      ],
      "size_pixels": 48
    },
    {
      "type": "circle",
      "color": "yellow",
      "size_category": "medium",
      "position": [
        388,
        417
      ],
      "size_pixels": 112
    },
    {
      "type": "circle",
      "color": "orange",
      "size_category": "small",
      "position": [
        473,
        543
      ],
      "size_pixels": 36
    }
  ]
}