{
  "difficulty": "hard",
  "image_index": 12359,
  "total_shapes": 5,
  "shapes": [
    {
      "type": "diamond",
      "color": "light_purple",
      "size_category": "medium",
      "position": [
        491,
        357
      ],
      "size_pixels": 130
    },
    {
      "type": "triangle",
      "color": "pale_blue",
      "size_category": "medium",
      "position": [
        209,
        390
      ],
      "size_pixels": 136
    },
    {
      "type": "hexagon",
      "color": "soft_purple",
      "size_category": "medium",
      "position": [
        326,
        227
      ],
      "size_pixels": 130
    },
    {
      "type": "triangle",
      "color": "pink",
      "size_category": "small",
      "position": [
        481,
        522
      ],
      "size_pixels": 48
    },
    {
      "type": "square",
      "color": "light_purple",
      "size_category": "medium",
      "position": [
        321,
        519
      ],
      "size_pixels": 100
    }
  ]
}