{
  "difficulty": "hard",
  "image_index": 16535,
  "total_shapes": 7,
  "shapes": [
    {
      "type": "hexagon",
      "color": "light_purple",
      "size_category": "large",
      "position": [
        224,
        392
      ],
      "size_pixels": 218
    },
    {
      "type": "star",
      "color": "mint",
      "size_category": "medium",
      "position": [
        160,
        199
      ],
      "size_pixels": 124
    },
    {
      "type": "rectangle",
      "color": "beige",
      "size_category": "medium",
      "position": [
        467,
        393
      ],
      "size_pixels": 124
    },
    {
      "type": "hexagon",
      "color": "light_purple",
      "size_category": "medium",
      "position": [
        412,
        214
      ],
      "size_pixels": 140
    },
    {
      "type": "hexagon",
      "color": "soft_purple",
      "size_category": "small",
      "position": [
        137,
        55
      ],
      "size_pixels": 42
    },
    {
      "type": "square",
      "color": "pale_mint",
      "size_category": "small",
      "position": [
        267,
        212
      ],
      "size_pixels": 40
    },
    {
      "type": "heart",
      "color": "light_green",
      "size_category": "medium",
      "position": [
        271,
        110
      ],
      "size_pixels": 118
    }
  ]
}