{
  "difficulty": "hard",
  "image_index": 4070,
  "total_shapes": 6,
  "shapes": [
    {
      "type": "square",
      "color": "yellow",
      "size_category": "medium",
      "position": [
        434,
        275
      ],
      "size_pixels": 124
    },
    {
      "type": "triangle",
      "color": "purple",
      "size_category": "medium",
      "position": [
        117,
        383
      ],
      "size_pixels": 96
    },
    {
      "type": "hexagon",
      "color": "soft_blue",
      "size_category": "small",
      "position": [
        140,
        224
      ],
      "size_pixels": 46
    },
    {
      "type": "star",
      "color": "light_pink",
      "size_category": "small",
      "position": [
        402,
        464
      ],
      "size_pixels": 34
    },
    {
      "type": "hexagon",
      "color": "pale_mint",
      "size_category": "medium",
      "position": [
        227,
        109
      ],
      "size_pixels": 132
    },
    {
      "type": "hexagon",
      "color": "mint",
      "size_category": "small",
      "position": [
        358,
        367
      ],
      "size_pixels": 58
    }
  ]
}