{
  "difficulty": "hard",
  "image_index": 293,
  "total_shapes": 5,
  "shapes": [
    {
      "type": "rectangle",
      "color": "light_mint",
      "size_category": "large",
      "position": [
        191,
        146
      ],
      "size_pixels": 234
    },
    {
      "type": "heart",
      "color": "light_pink",
      "size_category": "medium",
      "position": [
        190,
        457
      ],
      "size_pixels": 96
    },
    {
      "type": "triangle",
      "color": "light_green",
      "size_category": "large",
      "position": [
        446,
        379
      ],
      "size_pixels": 252
    },
    {
      "type": "star",
      "color": "pale_mint",
      "size_category": "medium",
      "position": [
        498,
        161
      ],
      "size_pixels": 130
    },
    {
      "type": "diamond",
      "color": "light_green",
      "size_category": "small",
      "position": [
        234,
        306
      ],
      "size_pixels": 38
    }
  ]
}