{
  "difficulty": "hard",
  "image_index": 15896,
  "total_shapes": 5,
  "shapes": [
    {
      "type": "circle",
      "color": "beige",
      "size_category": "medium",
      "position": [
        268,
        430
      ],
      "size_pixels": 110
    },
    {
      "type": "rectangle",
      "color": "beige",
      "size_category": "small",
      "position": [
        308,
        158
      ],
      "size_pixels": 56
    },
    {
      "type": "pentagon",
      "color": "soft_purple",
      "size_category": "medium",
      "position": [
        467,
        492
      ],
      "size_pixels": 136
    },
    {
      "type": "oval",
      "color": "soft_blue",
      "size_category": "small",
      "position": [
        162,
        219
      ],
      "size_pixels": 44
    },
    {
      "type": "oval",
      "color": "pink",
      "size_category": "medium",
      "position": [
        164,
        100
      ],
      "size_pixels": 134
    }
  ]
}