{
  "difficulty": "hard",
  "image_index": 18275,
  "total_shapes": 7,
  "shapes": [
    {
      "type": "circle",
      "color": "beige",
      "size_category": "medium",
      "position": [
        397,
        459
      ],
      "size_pixels": 94
    },
    {
      "type": "heart",
      "color": "light_green",
      "size_category": "medium",
      "position": [
        164,
        450
      ],
      "size_pixels": 94
    },
    {
      "type": "pentagon",
      "color": "soft_blue",
      "size_category": "small",
      "position": [
        482,
        246
      ],
      "size_pixels": 36
    },
    {
      "type": "star",
      "color": "pink",
      "size_category": "small",
      "position": [
        525,
        159
      ],
      "size_pixels": 38
    },
    {
      "type": "triangle",
      "color": "light_green",
      "size_category": "medium",
      "position": [
        382,
        180
      ],
      "size_pixels": 148
    },
    {
      "type": "oval",
      "color": "pink",
      "size_category": "small",
      "position": [
        77,
        270
      ],
      "size_pixels": 60
    },
    {
      "type": "hexagon",
      "color": "soft_blue",
      "size_category": "medium",
      "position": [
        223,
        99
      ],
      "size_pixels": 132
    }
  ]
}