{
  "difficulty": "hard",
  "image_index": 3430,
  "total_shapes": 6,
  "shapes": [
    {
      "type": "diamond",
      "color": "soft_blue",
      "size_category": "large",
      "position": [
        412,
        290
      ],
      "size_pixels": 266
    },
    {
      "type": "hexagon",
      "color": "pale_blue",
      "size_category": "small",
      "position": [
        122,
        141
      ],
      "size_pixels": 46
    },
    {
      "type": "star",
      "color": "light_pink",
      "size_category": "medium",
      "position": [
        256,
        486
      ],
      "size_pixels": 122
    },
    {
      "type": "diamond",
      "color": "soft_purple",
      "size_category": "medium",
      "position": [
        141,
        365
      ],
      "size_pixels": 122
    },
    {
      "type": "square",
      "color": "purple",
      "size_category": "small",
      "position": [
        440,
        527
      ],
      "size_pixels": 58
    },
    {
      "type": "diamond",
      "color": "yellow",
      "size_category": "small",
      "position": [
        524,
        59
      ],
      "size_pixels": 50
    }
  ]
}