{
  "difficulty": "hard",
  "image_index": 13761,
  "total_shapes": 6,
  "shapes": [
    {
      "type": "rectangle",
      "color": "orange",
      "size_category": "medium",
      "position": [
        444,
        400
      ],
      "size_pixels": 94
    },
    {
      "type": "heart",
      "color": "orange",
      "size_category": "small",
      "position": [
        297,
        499
      ],
      "size_pixels": 42
    },
    {
      "type": "heart",
      "color": "pale_mint",
      "size_category": "small",
      "position": [
        211,
        497
      ],
      "size_pixels": 58
    },
    {
      "type": "triangle",
      "color": "soft_blue",
      "size_category": "large",
      "position": [
        397,
        185
      ],
      "size_pixels": 220
    },
    {
      "type": "triangle",
      "color": "light_pink",
      "size_category": "medium",
      "position": [
        92,
        395
      ],
      "size_pixels": 100
    },
    {
      "type": "diamond",
      "color": "pale_blue",
      "size_category": "small",
      "position": [
        65,
        544
      ],
      "size_pixels": 62
    }
  ]
}