{
  "difficulty": "hard",
  "image_index": 1007,
  "total_shapes": 6,
  "shapes": [
    {
      "type": "heart",
      "color": "light_mint",
      "size_category": "small",
      "position": [
        558,
        209
      ],
      "size_pixels": 34
    },
    {
      "type": "square",
      "color": "light_pink",
      "size_category": "medium",
      "position": [
        326,
        307
      ],
      "size_pixels": 128
    },
    {
      "type": "hexagon",
      "color": "light_green",
      "size_category": "small",
      "position": [
        79,
        351
      ],
      "size_pixels": 50
    },
    {
      "type": "triangle",
      "color": "pink",
      "size_category": "medium",
      "position": [
        191,
        475
      ],
      "size_pixels": 136
    },
    {
      "type": "square",
      "color": "pale_blue",
      "size_category": "small",
      "position": [
        99,
        164
      ],
      "size_pixels": 54
    },
    {
      "type": "hexagon",
      "color": "light_green",
      "size_category": "small",
      "position": [
        58,
        44
      ],
      "size_pixels": 48
    }
  ]
}