{
  "difficulty": "hard",
  "image_index": 5122,
  "total_shapes": 5,
  "shapes": [
    {
      "type": "diamond",
      "color": "purple",
      "size_category": "medium",
      "position": [
        191,
        488
      ],
      "size_pixels": 116
    },
    {
      "type": "triangle",
      "color": "orange",
      "size_category": "large",
      "position": [
        251,
        181
      ],
      "size_pixels": 224
    },
    {
      "type": "square",
      "color": "light_pink",
      "size_category": "small",
      "position": [
        84,
        506
      ],
      "size_pixels": 56
    },
    {
      "type": "triangle",
      "color": "light_purple",
      "size_category": "medium",
      "position": [
        450,
        430
      ],
      "size_pixels": 124
    },
    {
      "type": "square",
      "color": "light_pink",
      "size_category": "small",
      "position": [
        536,
        267
      ],
      "size_pixels": 50
    }
  ]
}