{
  "difficulty": "hard",
  "image_index": 8815,
  "total_shapes": 5,
  "shapes": [
    {
      "type": "diamond",
      "color": "light_pink",
      "size_category": "medium",
      "position": [
        326,
        303
      ],
      "size_pixels": 148
    },
    {
      "type": "circle",
      "color": "teal",
      "size_category": "medium",
      "position": [
        290,
        510
      ],
      "size_pixels": 130
    },
    {
      "type": "square",
      "color": "pale_blue",
      "size_category": "small",
      "position": [
        360,
        186
      ],
      "size_pixels": 42
    },
    {
      "type": "oval",
      "color": "soft_blue",
      "size_category": "small",
      "position": [
        235,
        171
      ],
      "size_pixels": 34
    },
    {
      "type": "star",
      "color": "light_blue",
      "size_category": "small",
      "position": [
        507,
        127
      ],
      "size_pixels": 44
    }
  ]
}