{
  "difficulty": "hard",
  "image_index": 9178,
  "total_shapes": 6,
  "shapes": [
    {
      "type": "pentagon",
      "color": "yellow",
      "size_category": "small",
      "position": [
        170,
        255
      ],
      "size_pixels": 58
    },
    {
      "type": "triangle",
      "color": "light_purple",
      "size_category": "medium",
      "position": [
        93,
        146
      ],
      "size_pixels": 106
    },
    {
      "type": "pentagon",
      "color": "pink",
      "size_category": "small",
      "position": [
        359,
        163
      ],
      "size_pixels": 40
    },
    {
      "type": "circle",
      "color": "pale_mint",
      "size_category": "small",
      "position": [
        269,
        139
      ],
      "size_pixels": 48
    },
    {
      "type": "heart",
      "color": "light_purple",
      "size_category": "medium",
      "position": [
        235,
        446
      ],
      "size_pixels": 102
    },
    {
      "type": "diamond",
      "color": "light_purple",
      "size_category": "large",
      "position": [
        457,
        285
      ],
      "size_pixels": 228
    }
  ]
}