{
  "difficulty": "hard",
  "image_index": 9464,
  "total_shapes": 5,
  "shapes": [
    {
      "type": "pentagon",
      "color": "pink",
      "size_category": "medium",
      "position": [
        240,
        491
      ],
      "size_pixels": 146
    },
    {
      "type": "diamond",
      "color": "light_green",
      "size_category": "large",
      "position": [
        157,
        265
      ],
      "size_pixels": 268
    },
    {
      "type": "pentagon",
      "color": "light_green",
      "size_category": "small",
      "position": [
        481,
        311
      ],
      "size_pixels": 52
    },
    {
      "type": "oval",
      "color": "light_purple",
      "size_category": "large",
      "position": [
        459,
        462
      ],
      "size_pixels": 196
    },
    {
      "type": "star",
      "color": "light_green",
      "size_category": "medium",
      "position": [
        323,
        86
      ],
      "size_pixels": 112
    }
  ]
}