{
  "difficulty": "hard",
  "image_index": 566,
  "total_shapes": 7,
  "shapes": [
    {
      "type": "pentagon",
      "color": "orange",
      "size_category": "medium",
      "position": [
        417,
        375
      ],
      "size_pixels": 146
    },
    {
      "type": "heart",
      "color": "light_pink",
      "size_category": "medium",
      "position": [
        142,
        434
      ],
      "size_pixels": 114
    },
    {
      "type": "star",
      "color": "lavender",
      "size_category": "small",
      "position": [
        254,
        392
      ],
      "size_pixels": 42
    },
    {
      "type": "oval",
      "color": "teal",
      "size_category": "medium",
      "position": [
        292,
        160
      ],
      "size_pixels": 116
    },
    {
      "type": "diamond",
      "color": "light_blue",
      "size_category": "small",
      "position": [
        358,
        522
      ],
      "size_pixels": 40
    },
    {
      "type": "diamond",
      "color": "purple",
      "size_category": "medium",
      "position": [
        508,
        175
      ],
      "size_pixels": 144
    },
    {
      "type": "oval",
      "color": "teal",
      "size_category": "small",
      "position": [
        423,
        501
      ],
      "size_pixels": 42
    }
  ]
}