{
  "difficulty": "hard",
  "image_index": 6979,
  "total_shapes": 6,
  "shapes": [
    {
      "type": "rectangle",
      "color": "soft_purple",
      "size_category": "medium",
      "position": [
        151,
        356
      ],
      "size_pixels": 96
    },
    {
      "type": "star",
      "color": "light_pink",
      "size_category": "large",
      "position": [
        424,
        301
      ],
      "size_pixels": 266
    },
    {
      "type": "triangle",
      "color": "light_blue",
      "size_category": "small",
      "position": [
        234,
        542
      ],
      "size_pixels": 46
    },
    {
      "type": "rectangle",
      "color": "pale_blue",
      "size_category": "small",
      "position": [
        526,
        501
      ],
      "size_pixels": 44
    },
    {
      "type": "circle",
      "color": "soft_purple",
      "size_category": "medium",
      "position": [
        135,
        161
      ],
      "size_pixels": 114
    },
    {
      "type": "circle",
      "color": "orange",
      "size_category": "small",
      "position": [
        356,
        62
      ],
      "size_pixels": 48
    }
  ]
}