{
  "difficulty": "hard",
  "image_index": 17878,
  "total_shapes": 6,
  "shapes": [
    {
      "type": "circle",
      "color": "pale_mint",
      "size_category": "medium",
      "position": [
        155,
        224
      ],
      "size_pixels": 102
    },
    {
      "type": "triangle",
      "color": "beige",
      "size_category": "large",
      "position": [
        395,
        150
      ],
      "size_pixels": 216
    },
    {
      "type": "star",
      "color": "light_green",
      "size_category": "large",
      "position": [
        323,
        381
      ],
      "size_pixels": 224
    },
    {
      "type": "star",
      "color": "soft_purple",
      "size_category": "small",
      "position": [
        45,
        269
      ],
      "size_pixels": 50
    },
    {
      "type": "pentagon",
      "color": "light_purple",
      "size_category": "small",
      "position": [
        535,
        460
      ],
      "size_pixels": 54
    },
    {
      "type": "heart",
      "color": "lavender",
      "size_category": "medium",
      "position": [
        157,
        531
      ],
      "size_pixels": 98
    }
  ]
}