{
  "difficulty": "easy",
  "image_index": 2,
  "total_shapes": 3,
  "shapes": [
    {
      "type": "square",
      "color": "light_blue",
      "size_category": "medium",
      "position": [
        291,
        105
      ],
      "size_pixels": 88
    },
    {
      "type": "circle",
      "color": "orange",
      "size_category": "medium",
      "position": [
        145,
        227
      ],
      "size_pixels": 64
    },
    {
      "type": "rectangle",
      "color": "pink",
      "size_category": "medium",
      "position": [
        261,
        245
      ],
      "size_pixels": 78
    }
  ]
}