{
  "difficulty": "easy",
  "image_index": 11920,
  "total_shapes": 3,
  "shapes": [
    {
      "type": "square",
      "color": "orange",
      "size_category": "medium",
      "position": [
        223,
        86
      ],
      "size_pixels": 98
    },
    {
      "type": "rectangle",
      "color": "pink",
      "size_category": "medium",
      "position": [
        161,
        245
      ],
      "size_pixels": 90
    },
    {
      "type": "circle",
      "color": "teal",
      "size_category": "medium",
      "position": [
        322,
        135
      ],
      "size_pixels": 80
    }
  ]
}