{
  "difficulty": "easy",
  "image_index": 1259,
  "total_shapes": 3,
  "shapes": [
    {
      "type": "rectangle",
      "color": "light_green",
      "size_category": "medium",
      "position": [
        153,
        230
      ],
      "size_pixels": 76
    },
    {
      "type": "triangle",
      "color": "soft_purple",
      "size_category": "medium",
      "position": [
        246,
        286
      ],
      "size_pixels": 60
    },
    {
      "type": "circle",
      "color": "soft_purple",
      "size_category": "medium",
      "position": [
        214,
        87
      ],
      "size_pixels": 72
    }
  ]
}