{
  "difficulty": "easy",
  "image_index": 15831,
  "total_shapes": 3,
  "shapes": [
    {
      "type": "rectangle",
      "color": "light_blue",
      "size_category": "medium",
      "position": [
        92,
        110
      ],
      "size_pixels": 94
    },
    {
      "type": "square",
      "color": "beige",
      "size_category": "medium",
      "position": [
        95,
        336
      ],
      "size_pixels": 74
    },
    {
      "type": "triangle",
      "color": "pink",
      "size_category": "medium",
      "position": [
        208,
        302
      ],
      "size_pixels": 94
    }
  ]
}