{
  "difficulty": "easy",
  "image_index": 6619,
  "total_shapes": 3,
  "shapes": [
    {
      "type": "triangle",
      "color": "light_mint",
      "size_category": "medium",
      "position": [
        102,
        122
      ],
      "size_pixels": 98
    },
    {
      "type": "square",
      "color": "teal",
      "size_category": "medium",
      "position": [
        263,
        100
      ],
      "size_pixels": 62
    },
    {
      "type": "square",
      "color": "beige",
      "size_category": "medium",
      "position": [
        271,
        204
      ],
      "size_pixels": 96
    }
  ]
}