{
  "difficulty": "easy",
  "image_index": 7635,
  "total_shapes": 3,
  "shapes": [
    {
      "type": "triangle",
      "color": "pink",
      "size_category": "medium",
      "position": [
        168,
        345
      ],
      "size_pixels": 70
    },
    {
      "type": "rectangle",
      "color": "light_blue",
      "size_category": "medium",
      "position": [
        141,
        106
      ],
      "size_pixels": 92
    },
    {
      "type": "square",
      "color": "light_purple",
      "size_category": "medium",
      "position": [
        174,
        229
      ],
      "size_pixels": 96
    }
  ]
}